typePrint/__init__.py
typePrint/typeprint.py
typeprint-0.0.2.dist-info/LICENSE
typeprint-0.0.2.dist-info/METADATA
typeprint-0.0.2.dist-info/WHEEL
typeprint-0.0.2.dist-info/top_level.txt
typeprint-0.0.2.dist-info/RECORD
